{"Amirgadh": ["Ajapur Mota", "Ajapur Vanka", "Ambapani", "Amirgadh", "Awal", "Awala (Arniwada)", "Balundra", "Bantawada", "Bhamariya", "Bhayla", "Chikanvas", "Dabhchatra", "Dabhela", "Dabheli", "Deri", "Dhanpura", "Dhanpura (Dholiya)", "Dholia", "Dungarpura", "Gadhada", "Ganji", "Gavara", "Ghanghu", "Ghanta", "Ghoda", "Iqbalgadh", "Isvani", "Jethi", "Jorapura (Amirgadh)", "Juni Roh", "Juni Roh Sarotri", "Kakwada", "Kali Mati", "Kanpura", "Kansaravid", "Kapasiya", "Karaza", "Karmadi", "Kengora", "Khajuriya", "Khapa", "Khapara", "Khara", "Khari", "Khemarajiya", "Khuniya", "Kidotar", "Laxmipura (Amirgadh)", "Mandaliya", "Manpuriya", "Nichlo Bandh", "Pedcholi", "Rabaran", "Rabariya", "Rajpuriya", "Rampura (Vadla)", "Sarotra", "Savaniya", "Sonwadi", "Surela", "Tadholi", "Umarkot", "Uplo Bandh", "Vagdadi", "Vaghoriya", "Vera", "Virampur", "Zaba", "Zanzarvav"], "Bhabhar": ["Abala", "Abasana", "Asana", "Balodhan", "Barvala", "Beda", "Bhabhar Juna", "Bhabhar Nava", "Bhem Bordi", "Bhodaliya", "Buretha", "Chachasana", "Chaladara", "Chatara", "Chembuva", "Chichodara", "Devkapdi", "Dhenkwadi", "Gangun", "Gosan", "Harkudiya", "Indarva Juna", "Indarva Nava", "Jasanwada", "Jorvada", "Kaprupur", "Karela", "Khadosan", "Khara", "Khari Paldi", "Kuvala", "Lunsela", "Manpura Bhabhar", "Mera", "Mespura", "Mitha", "Moti Sari", "Nesda", "Radakiya", "Roita", "Runi", "Sanesda", "Sanva", "Suthar Nesdi", "Tanvad", "Tetarva", "Ujjanwada", "Undai", "Vadana", "Vadpag", "Vajapur Juna", "Vajapur Nava", "Vavdi"], "Danta": ["Abhapura", "Aderan (Danta)", "Aderan (Mankadi)", "Amarpura", "Ambaghanta", "Ambaji (CT)", "Amblimal", "Amloi", "Balvantpura", "Bamaniya", "Bamnoj", "Banodara", "Barvas", "Beda", "Bedapani", "Begadiyavas", "Bhachadiya", "Bhadramal", "Bhankhri", "Bhanpur", "Bhavangadh", "Bordiyala", "Chhota Bamodara", "Chhota Pipodara", "Chikhla", "Chokibor", "Chorasan", "Chori", "Dabhchatra", "Dalpura", "Danta", "Dericharda", "Devaliyavali Vav", "Dhabani Vav", "Dhagadiya", "Dhamanva", "Dhareda", "Dhrangivas", "Dhunali", "Divdi", "Gadh (Danta)", "Gadh (Mahudi)", "Gajipur", "Ganapipli", "Ganchhera", "Gangva", "Ghantodi", "Ghodatankani", "Ghorad", "Godhani", "Gothada", "Guda", "Hadad", "Harigadh", "Harivav", "Hathi Pagala", "Hedo", "Jagatapura", "Jalana", "Jambera", "Jamru", "Jasvantgadh", "Jasvantpura (Danta)", "Jasvantpura (Hadad)", "Jasvapura (Mankdi)", "Javara", "Jetvas", "Jharivav", "Jhumfali", "Jitpur", "Jodhsar", "Jorapura", "Kanabiyavas", "Kanagar", "Kansa", "Kantivas", "Karanpur", "Kengora", "Kesarpura", "Khaivad", "Khandhora", "Khantani Magari", "Khatal", "Kherani Umbari", "Khermal", "Kheroj", "Khokhar Bili", "Khokhariyavas", "Kodaravi Ranpur", "Koteshvar", "Koylapur", "Kukadi", "Kumbhariya", "Kundel", "Kunvarsi", "Lotol", "Machakoda", "Madhusudanpura", "Magvas", "Mahobatgadh (Danta)", "Mahobatgadh (Hadad)", "Mahuda", "Mahudi", "Mal", "Manchhla", "Mandali", "Mandaliyala", "Mankanchampa", "Mankdi", "Manpur (Ghorad)", "Manpur (Pethapur)", "Miranvas", "Mor Dungara", "Mota Bamodara", "Mota Pipodara", "Motasada", "Motipura", "Nagel", "Naivada", "Nanasada", "Nani Tudiya", "Nargadh", "Navaniya", "Navanu Padar", "Navavas (Danta)", "Navovas (Hadad)", "Padaliya", "Panchha", "Paniyari", "Panudara", "Pasiya", "Pataliya", "Pethapur", "Pipalavali Vav", "Pith (Navanagar)", "Pruthvirajgadh", "Punjpur", "Raghpur", "Rangpur", "Rani Umbari", "Ranika", "Ranol", "Ranpur", "Ratanpur", "Rayaniya", "Rinchhadi", "Ruppura", "Rupvas", "Samaiya", "Sanali", "Sandhosi", "Santpur", "Sarakala", "Sarhad Chhapri", "Savaipura", "Sembal", "Sembaliya", "Sembalpani", "Senkda", "Siyavada", "Solsanda", "Sultanpur", "Taleti", "Tarangda", "Tekari", "Thalvada", "Thana", "Toda", "Toraniya", "Udavas", "Umbara", "Umedpura", "Unodara", "Vadnal", "Vadusan", "Vadvera", "Vagada Kyari", "Vaghdacha", "Vajasana", "Vasi", "Vekari", "Velvada", "Vijalasan", "Viramveri", "Virpur (Lotol)", "Virpur(Hadad)"], "Dantiwada": ["Akoli", "Arkhi", "Atal", "Bhadali (Zat)", "Bhadli Kotha", "Bhakhar Moti", "Bhakhar Nani", "Bhakodar", "Bhandotra", "Bhilachal", "Bhilada", "Chodungri", "Dangiya", "Dantiwada", "Deri", "Dhaneri", "Dhaniyawada", "Fatepura (Dhanawada)", "Gangudara", "Ganguwada", "Ganodara", "Godh", "Gundari", "Hariyawada", "Jegol", "Jorapura (Lodpa)", "Jorapura Bhadli", "Kotda (Jegol)", "Lakhanasar", "Lodpa", "Mahudi Moti", "Mahudi Nani", "Malpuriya", "Marwada", "Nandotra (Brahmanvas)", "Nandotra (Thakorvas)", "Nilpur", "Odhava", "Panswal", "Panthawada", "Rajkot", "Rampura (Panswal)", "Rampura Mahudi", "Ramsida (Chhapra)", "Ranol", "Ratanpur", "Santarwada", "Satsan", "Shergadh Odhava", "Sikariya", "Talenagar", "Vadvas", "Vaghrol", "Vagor", "Vavdhara", "Velavas", "Zat"], "Deesa": ["Agdol", "Akhol Moti", "Akhol Nani", "Aseda", "Baiwada", "Balodhar", "Bhachalva", "Bhadath", "Bhadra", "Bhadramali", "Bhildi", "Bhoyan", "Bodal", "Bural", "Chandaji Golia", "Chatrala", "Chhatrala", "Chora", "Dama", "Dasanavas", "Davas", "Dedol", "Dhanavada", "Dhanpura", "Dharisana", "Dharpada", "Dhedhal", "Dhuva", "Fagudra", "Fatepura", "Genaji rabari Golia", "Ghada", "Gharnal Moti", "Gharnal Nani", "Gugal", "Javal", "Jhabadiya", "Jherda", "Jorapura", "Juna Deesa", "Kamodi", "Kanajhara", "Kant", "Kasari", "Khadosan", "Khentva", "Kochasana", "Kotha", "Kuchavada", "Kumpat", "Kunvara Padar", "LILAPURA", "Latiya", "Laxmipura", "Lorvada", "Lunpur", "Mahadeviya", "Malgadh", "Manekpura", "Meda", "Morthal Golia", "Mudetha", "Nagafana", "Nava", "Nava Bhildi (CT)", "Nava Deesa", "Nesda Juna", "Nesda Nava", "Odhava", "Paldi", "Pamaru", "Pechhdal", "Rajpur", "Rampura", "Ramsan", "Ramun", "Ramvas", "Ranpur Athamno Vas", "Ranpur Ugamno Vas", "Ranpur Vachlovas", "Rasana Mota", "Rasana Nana", "Ratanpura", "Robas Moti", "Robas Nani", "Sadarpur", "Samau Motavas", "Samau Nanavas", "Sanath", "Sandiya", "Sarat", "Saviyana", "Shamsherpura", "Sherganj", "Sherpura", "Sodapur", "Sotambla", "Soyla", "Sunthiya", "Talegadh", "Taleganj", "Talepura", "Tetoda", "Thervada", "Vadaval", "Vadli Farm", "Vahara", "Varan", "Varnoda", "Vasada", "Vasna (Juna Deesa)", "Velavapura", "Viruna", "Viruvada", "Vithodar", "Yavarganj", "Yavarpura", "Zenal"], "Deodar": ["Bhadkasar", "Bhagwanpura", "Bhesana", "Boda", "Chagwada", "Chamanpura", "Chibhda", "Daua", "Delwada", "Deodar (CT)", "Dhanakwada", "Dhrandav", "Dhrandvada", "Dhunsol", "Duchakwada", "Forna", "Gangol", "Goda", "Golvi", "Golvo", "Jada", "Jalodha", "Jasali", "Khanodar", "Kotarwada", "Kotda Deodar", "Kotda Forna", "Kunvarva", "Kunvata", "Liladhar", "Ludara", "Makhanu", "Manpura Dhunsol", "Manpura Jalodha", "Mesra", "Mojru Juna", "Mojru Nava", "Mulakpur", "Narana", "Nava", "Navapura", "Nokha", "Odha", "Ogadpura", "Paldi", "Raiya", "Rampura", "Rantila", "Ravel", "Salpura", "Samla Vadana", "Sanadar", "Sanav", "Sardarpura (Jasali)", "Sardarpura (Ravel)", "Sesan Juna", "Sesan Nava", "Soni", "Surana", "Vadiya", "Vakha", "Vatam Juna", "Vatam Nava"], "Dhanera": ["Aeta", "Alwada", "Anapur Chhota", "Anapurgadh", "Asiya", "Bapla", "Bhajna", "Bhatib", "Bhatram", "Charda", "Chhindivadi", "Dedha", "Dhakha", "Dhanera", "Dhanpura (Kheda)", "Dharnodhar", "Dugdol Moti", "Dugdol Nani", "Edal", "Fatepura (Malotra)", "Gola", "Hadta", "Jadi", "Jadiya", "Janali", "Jiwana", "Jorapura (Dhakha)", "Karadhani", "Khangan", "Khaprol", "Khimat", "Kotda (Dhakha)", "Kotda (Raviya)", "Kumar", "Kundi", "Kunwarla", "Lawara", "Lelava", "Magarawa", "Malotra", "Mandal", "Mewada", "Mota Meda", "Nana Meda", "Nanuda", "Negala", "Nenava", "Pengiya", "Rajoda", "Rampura (Vaghpura)", "Rampura Chhota", "Rampura Mota", "Ramuna", "Ravi", "Raviya", "Runi", "Sabawadi", "Samalwada", "Sankad", "Saral", "Sera", "Shergadh (Jadiya)", "Silasana", "Siya", "Sodal", "Sotwada", "Talegadh", "Thawar", "Vachhdal", "Vachhol", "Vaktapura", "Valer", "Vasan", "Vasda", "Vinchhivadi", "Virol", "Voda", "Yavarpura"], "Kankrej": ["Adhgam", "Akoli Maharajvas", "Akoli Thakorvas", "Amarnesda", "Amblivas", "Amblun", "Anandpura", "Anganwada", "Arduvada", "Arniwada", "Balochpura", "Bhadrevadi", "Bhalgam", "Bhavnagar", "Bukoli", "Changa", "Chekhala", "Chembla", "Chimangadh", "Devdarbar", "Devpura", "Dhanera", "Dudasan", "Dugrasan", "Fategadh", "Fatepura", "Gothada", "Gunthawada(Dalpatpura)", "Indramana", "Isarva", "Jakhel", "Jaliya", "Jamana Padar", "Jotada", "Kakar", "Kamboi", "Kantheriya", "Karsanpura", "Kasalpura", "Kasara", "Kashipura", "Katediya", "Khariya", "Khasa", "Khengarpura", "Khimana(Palodar Na Vas)", "Khoda", "Khodla", "Kudva", "Kunvarava", "Laxmipura", "Maidkol", "Mandala", "Mangalpura Nagot", "Manpur (Shihori)", "Manpura (Un)", "Mota Jampur", "Nagot", "Nana Jampur", "Nanota", "Nasaratpura", "Nathpura", "Nava", "Nekariya", "Nekoi", "Odha", "Padar", "Padardi", "Rajpur", "Ranakpur", "Ranawada (Jagiri)", "Ranawada (Khalsa)", "Raner", "Ratangadh", "Ratanpura (Shihori)", "Ratanpura (Un)", "Raviyana", "Runi", "Ruppura", "Ruvel", "Samanva", "Savpura", "Shihori", "Shirwada", "Shiya", "Sohanpura", "Sudrosan", "Tana", "Tatiyana", "Tervada", "Thali", "Thara", "Totana", "Ucharpi", "Umbri", "Un", "Vada", "Valpura", "Varasada", "Vibhanesda", "Vithlod", "Zalmor"], "Lakhani": ["Achhavadiya", "Agthala", "Asasan", "Bhakadiyal", "Bhimgadh", "Chalva", "Chekra", "Chitroda", "Deka", "Dera", "Detal Darbari", "Detal Duva", "Devsari", "Dharanva", "Dhroba", "Dhunsol", "Dodana", "Dodiya", "Gamdi", "Ganata", "Gela", "Ghana", "Godha", "Jadiyali", "Jasara", "Jhakol", "Kamoda", "Katarva", "Kherola", "Kotda", "Kuda", "Kuwana", "Lakhani", "Lalpur", "Lavana", "Lembau", "Madal", "Makdala", "Manaki", "Matu", "Moral", "Mota Kapra", "Nana Kapra", "Nandla", "Nani", "Peparal", "Peplu", "Shergadh", "Taruwa", "Vajegadh", "Vakvada", "Vasna (Kuda)", "Vasna (Vatam)"], "Palanpur": ["Akedi", "Akesan", "Aligadh", "Ambaliyal", "Ambetha", "Angola", "Antroli", "Asmapura (Gola)", "Asmapura (Karjoda)", "Badargadh", "Badarpura (Bhutedi)", "Badarpura (Kalusana)", "Badarpura (Khodla)", "Bhagal (Jagana) (CT)", "Bhagal (Pipli)", "Bhatamal Moti", "Bhatamal Nani", "Bhatwadi", "Bhavisana", "Bhutedi", "Chadotar", "Chandisar", "Chekhala", "Chitrasani", "Dalwada", "Delwada", "Dhandha", "Dhaniyana", "Dhelana", "Esbipura", "Fatepur", "Gadh", "Galwada", "Gathaman", "Godh", "Gola", "Gopalpura", "Hasanpur", "Hathidra", "Hebatpur", "Hoda", "Jadial", "Jagana", "Jasleni", "Jaspuriya", "Jorapura Bhakhar", "Juvol", "Kamalpur", "Kanodar (CT)", "Karjoda", "Kharodiya", "Khasa", "Khemana", "Khodla", "Kotda (Bhakhar)", "Kotda (Chand Gadh)", "Kumbhalmer", "Kumbhasan", "Kumpar", "Kushakal", "Lalawada", "Laxmanpura", "Lunwa", "Madana (Dangiya)", "Madana (Gadh)", "Malan", "Malana", "Malpuriya", "Manaka", "Manpur (Karjoda)", "Merwada (Mahajan)", "Merwada (Ratanpur)", "Moriya", "Mota", "Nalasar", "Pakhanwa", "Palanpur (Rural) (Laxmipura) (OG)", "Parpada", "Patosan", "Pedagara", "Pipli", "Pirojpura(Tankani)", "Rajpur (Pakhanva)", "Rampura (Karaza)", "Ranawas", "Ranpuriya", "Ratanpur", "Ruppura", "Sadarpur", "Sagrosana", "Salempura", "Salla", "Sambarda", "Samdhi (Motavas)", "Samdhi (Nadhanivas)", "Samdhi Ranajivas", "Sangla", "Sangra", "Saripada", "Sasam", "Sedrasana", "Semodra", "Songadh", "Sundha", "Surajpura (Khe)", "Takarwada", "Talepura (Madana)", "Tokariya", "Ukarda", "Vadhana", "Vagda", "Varwadia", "Vasan", "Vasani", "Vasda (Fatepur)", "Vasda (Mujpur)", "Vasna (Jagana)", "Vedancha", "Virpur"], "SUIGAM": ["\"Nesda (Go)\"", "Benap", "Bharadava", "Bhatasana", "Boru", "Chala", "Dabhi", "Devpura (Suigam)", "Dhanana", "Dhrechana", "Dudhva", "Dudosan", "Dungala", "Garambadi", "Golap", "Harsad", "Jaloya", "Jelana", "Jorawargadh", "Kanothi", "Katav", "Khadol", "Koreti", "Kumbharkha", "Limbala", "Limbuni", "Madhpura", "Mamana", "Masali", "Meghpura", "Morwada", "Motipura", "Nadabet", "Navapura", "Padan", "Radka", "Radosan", "Rajpura", "Sedav", "Soneth", "Suigam", "Uchosan", "Vaghpura"], "Tharad": ["Abhepura", "Ajawada", "Antrol", "Arantva", "Asodar", "Betaliya", "Bevata", "Bhachar", "Bhadodar", "Bhalasara", "Bhapdi", "Bhapi", "Bhardasar", "Bhimpura", "Bhordu", "Bhorol", "Bhuriya", "Budhanpur", "Changada", "Charda", "Chhanasara", "Chotapa", "Chudmer", "DHESDA", "Dantiya", "Dedudi", "Deduva", "Del", "Delankot", "Didarada", "Dipda", "Dodgam", "Dolatpura", "Dudhva", "Duva", "Gadsisar", "Gagana", "Ganeshpura", "Ghantiyali", "Ghesda", "Ghodasar", "Hathawada", "Idhata", "Jadara", "Jamda", "Jampur", "Janadi", "Jandla", "Jetda", "Kamali", "Karanpura", "Karbun", "Karnasar", "Kasavi", "Kesargam", "Khanpur", "Kharakhoda", "Khengarpura", "Khoda", "Khorda", "Kiyal", "Kochala", "Kothigam", "Kumbhara", "Lakhapura", "Lendau", "Lodhnor", "Lorwada", "Lunal", "Lunawa", "Luvana (K)", "Mahadevpura", "Mahajanpura", "Malupur", "Mangrol", "Medhala", "Meghpura", "Miyal", "Morila", "Morthal", "Mota Mesara", "Moti Pavad", "Nagala", "Nana Mesara", "Nani Pavad", "Nanol", "Naroli", "Padadar", "Pathamda", "Patiyasara", "Pavadasan", "Pepar", "Piluda", "Pirgadh", "Radka", "Rah", "Rajkot", "Rampura", "Ranesari", "Ranpur", "Ratanpura", "Saba", "Sanadhar", "Sanavia", "Savarakha", "Savpura", "Sedla", "Sherau", "Sidhotara", "Takhuva", "Terol", "Tharad", "Therwada", "Undrana", "Untveliya", "Vadgamda", "Vaghasan", "Vajegadh", "Valadar", "Vami", "Vantdau", "Vara", "Vedala", "Zenta"], "Vadgam": ["Amadpura (Ghodiyal)", "Amadpura (Mumanvas)", "Amirpura", "Andhariya", "Badarpura", "Basu", "Bavalchudi", "Bhakhari", "Bhalgam", "Bhangrodiya", "Bharkawada", "Bharod", "Bhatvas", "Bhukhla", "Changa", "Changwada", "Chhaniyana", "Chhapi (CT)", "Chitroda", "Dalvana", "Dhanali", "Dhanpura", "Dharewada", "Dhori", "Dhota", "Edrana", "Fategadh", "Ghodiyal", "Gidasan Moti", "Gidasan Nani", "Hadmatiya", "Harde Vasana", "Hasanpur", "Hatavad", "Iqbalgadh", "Iqbalpura", "Islampura", "Jalotra", "Joita", "Juni Nagari", "Juni Sendhani", "Kabirpura", "Kaleda", "Kamalpura", "Karasanpura", "Karnala", "Kodarali", "Kodaram", "Kotadi", "Limboi", "Magarwada", "Mahi", "Majadar", "Majatpur", "Malosana", "Manpura", "Megal", "Mejarpura", "Memadpur", "Mepada", "Meta", "Mokeshvar", "Moriya", "Moteta", "Motipura", "Mumanvas", "Nagana", "Nagarpura", "Nalasar", "Nandotra", "Nanosana", "Navi Nagari", "Navi Sendhani", "Navisana", "Navo Vas", "Nizampura", "Paldi", "Panchada", "Pandva", "Parkhadi", "Pasvadal", "Pavthi", "Pepol", "Pilucha", "Pirojpura", "Rajosana", "Rupal", "Sabalpura", "Sakalana", "Salemkot", "Samsherpura", "Sardarpura", "Sherpura (Majadar)", "Sherpura (Sembhar)", "Sisrana", "Sukhpura", "Tajpura", "Teniwada", "Thalwada", "Thuvar", "Timbachudi", "Umrecha", "Vadgam", "Vagadadi", "Vansol", "Varasada", "Varnawada", "Varvadiya", "Vasana (Sembhar)", "Vesa"], "Vav": ["Achhuva", "Akoli", "Arjanpura", "Asaragam", "Asaravas", "Bahisara", "Baiyak", "Baluntri", "Baradvi", "Bhachali", "Bhadvel", "Bhakhari", "Bhankhod", "Bhatvar Vas", "Bhatvargam", "Bukna", "Chandangadh", "Chandarva", "Chatarpura", "Chothar Nesda", "Chotil", "Chuva", "Daiyap", "Dendava", "Dethali", "Devpura (Talsari)", "Dharadhara", "Dheriana", "Dhima", "Eta", "Fangadi", "Gambhirpura", "Golgam", "Haripura", "Ishvariya", "Janavada", "Jordiyali", "Kalyanpura", "Kareli", "Khardol", "Khimana Padar", "Khimanavas", "Kolava", "Kumbhardi", "Kundaliya", "Lalpura", "Lodrani", "Madka", "Malsan", "Mavsari", "Mithavi Charan", "Mithavi Rana", "Morikha", "Nalodar", "Panesada", "Pratappura", "Rabadi Padar", "Rachhena", "Radha Nesda", "Rampura", "Ravla", "Reluchi", "Sanval", "Sapreda", "Sardarpura", "Savpura", "Tadav", "Takhatpura (Dhima)", "Takhatpura (J)", "Tejpura", "Tithgam", "Tobha", "Uchpa", "Umedpura", "Vajiyasara", "Vasarda", "Vav", "Vavdi"]}