{"Bermo": ["BAIDKARO ANSH", "BERMO ANSH", "BODIA ANSH", "Baidkaro", "Bermo", "Bodia", "GOVINDPUR ANSH", "Gandke", "Gobindpur", "JARANGDIH ANSH", "Jarangdih", "Kurpania", "Lukubad", "jaridih"], "Chandankiyari": ["Adarkunri", "Agardi", "Aluara", "Amainagar", "Amdiha", "Amlabad (CT)", "Arita", "Asanbani", "Asanshol", "Babugram", "Babuigor", "Bangaria", "Banshara", "Banshgari", "Banshtora", "Barajor", "Baramesya", "Barda", "Barishabad", "Barkama", "Batbinor", "Batboa", "Bharajuri", "Bhojudih (CT)", "Bhuski", "Bindabanpur", "Birajdi", "Birkham", "Bodma", "Bogla", "Boryadi", "Chakparbad", "Chakpendra", "Chandankiari", "Chandipur", "Chandra", "Chhatatanr", "Chirda", "Damodarpur", "Damudi", "Darida", "Debgram", "Dhekbera", "Diborda", "Fatepur", "Galgaltanr", "Gamarya", "Gangudi", "Ghaghri", "Ghoragara", "Gopinathpur Alias Gosaindi", "Gorigram", "Gundlibhitha", "Gurri", "Jagidi", "Jashpur", "Jhabra", "Jhalbarda", "Jharna", "Kali Kapur", "Kanakchas", "Kanchanpur", "Karadi", "Karmatanr", "Kauria", "Kelyadag", "Kendulia", "Khedadi", "Kherabera", "Kulshara", "Kumirdoba", "Kusumkiari", "Laghla", "Lakshipur", "Lalpur", "Lanka", "Lututanr", "Machatanr", "Mahal", "Manpur", "Marra", "Mazoorubi", "Mohanpur", "Muktapur", "Nadiha", "Naradi", "Narkarai", "Nawadi", "Nayaban Alias Pabratanr", "Nekura", "Nerpurbanchak", "Nuniadi", "Palkiri", "Palkudri", "Parbahal", "Parbatpur", "Pathargarha", "Pathra", "Phulbahra", "Phusra", "Piparkudar", "Piprabera", "Polashdabar", "Rahinigara", "Rangametya", "Rangragara", "Ratanpur", "Sabna", "Saharjuri", "Sanrboa", "Shankhakunri", "Sharishakuri", "Shibbabudi", "Shimalkunri", "Silajuri", "Silphor", "Simulia", "Sitanala", "Surajyadi", "Sutribera", "Talgaria", "Tekora", "Tentulia", "Tilatanr", "Udaipur", "Udalbani", "Uparbandha"], "Chandrapura": ["Alargo", "Bandieo", "Bandih", "Budhsera", "Chadri", "Chandrapura (CT)", "Chirudih", "Dugda (CT)", "Fatehpur", "Ghatiyari", "Ghutwe", "Junori", "Karidugdho", "Karmatand", "Khalcho", "Kurumba", "Narra (CT)", "Nasiya", "Paplo", "Pipradih", "Raja Bera", "Rangamati", "Ratari", "Sijua", "Taranari", "Taranga", "Tarmi", "Telo (CT)", "Turio"], "Chas": ["Abra", "Adamdih", "Alkusa", "Amadhia", "Amadi", "Amuramu", "Andharteliya", "Ashudi", "Babudi", "Badhdih", "Bahadurpur", "Bamundanrika", "Banddih", "Bandhgora (CT)", "Bandhpuwa", "Bansa", "Baradi", "Barmasia", "Barpokharia", "Baruatand", "Baryadi", "Basantpur", "Belanja", "Belut", "Berani", "Bhagabandh", "Bhandro", "Bhawanipur", "Bhunyadarika", "Bijuliya", "Bishwanathdi", "Bishwanathdih", "Bodro", "Brindabanpur Alias Shatatanr", "Buribinora", "Chainpur", "Chakalia", "Chandaha", "Chetami", "Chhanrgoi", "Chiksia", "Chopatanr", "Chuatand", "Dabarbahal", "Dabka", "Demudih", "Dewanganj", "Dhandabar", "Dharampura", "Dhobani", "Dudigagar", "Dumarda", "Dumarjor", "Dungrighutu", "Durgapur", "Gamdidih", "Gariaghutu", "Ghatiali", "Girdhartand", "Gopalpur", "Gopidi", "Gopidih", "Gurguri", "Hutu Pathar", "Jala", "Janamdi", "Jaytara", "Jhapro", "Kala Pather", "Kamaldih", "Kandra", "Karmagora", "Kashijharia", "Kathwari", "Katka", "Kelyadabar", "Kendadih", "Keshridih", "Khamarbendih", "Khirabera", "Khuntadi", "Kolbendi", "Kumardaga", "Kumri", "Kura", "Kurarpur", "Kurma", "Kushma", "Leda", "Madhniya", "Mamar Kudar", "Mandladih", "Mango", "Maraphari", "Middha", "Mohanpur", "Mohoda", "Narayanpur", "Narkera", "Nawadih", "Niche Baruatand", "Nichitpur", "Paidadi", "Pailadi", "Pakariatand", "Parsabera", "Partand", "Phudnidih", "Pindajora", "Pokhanna", "Punrru", "Pupunki", "Radhanagar", "Raghunath Chak", "Rahorgora", "Ranichirka", "Raniganj Alias Chatitanr", "Ranipokhar", "Ritudih", "Santaldih", "Sardaha", "Satanpur", "Shiarda", "Shilphor", "Sialgajra", "Sijhua", "Simuliya", "Sindurpeti", "Sonabad", "Sunta", "Telmatiya", "Tetuliya", "Tiara", "Tughari", "Tupladih Station road", "Tupra", "Turidi", "Ulgara", "Usardi", "basa", "basgora", "bhatua", "gorawali", "hansabatu", "jamgodia", "karharia", "usirdih"], "Gomia": ["Aiyar", "Ambadih", "Ambatanr", "Ataundi", "BHURKUNDA", "Baghraiya", "Baigankeri", "Balia", "Banchatra", "Bandh", "Bandiha", "Baridari", "Barka Murpa", "Barki Sidhabara", "Barkichidri", "Barkipunu", "Bartua", "Bendi", "Bhitia", "Birsa", "Chagri", "Chatro Chati", "Chhotki Sidhbara", "Chidri Khurd", "Chilga", "Chipri", "Chitu", "Chorganwa", "Chotakipunu", "Chotka Murpa", "Chugnu", "Chute", "Dakasaram", "Danea", "Danra", "Daridag", "Derhabera", "Dhawaiya", "Dhendhe", "Dhudhmo", "Dumri", "Gangpur", "Gobhi Karmatanr", "Gopo", "Gose", "Gumia (CT)", "Gurudih", "HAZARI", "Halwe", "Haradgara", "Hardiam", "Hasir (CT)", "Honhe", "Hosir west", "Hurdag", "Hurlung", "JHIRKE", "Jagesar", "Jaharlong", "Jala", "Jamni Jara", "Jarea", "Jarkunda", "Jhumchi", "Jumrapahar", "KHAMHARA", "KHUDGADHA", "Kairatanr", "Kander", "Kari Kalan", "Kari Khurd", "Karma", "Katwari", "Keri", "Khakanda", "Khakhanda", "Kharna", "Kharwatanr", "Khirabera", "Khokhando", "Kodwatand", "Kunda", "Kurknalo", "Lalgarh", "Lalpania", "Lalpania (CT)", "Lawalang", "Lodhi", "Lugu Pahar", "MAHLITAND", "Magha", "Mahuatanr", "Mangro", "Morha", "Mukhchuma", "Murpa", "Naran", "Narkandi", "Nawadih", "Nawdanda", "Ocho", "PALANI", "PALIHARI GURUDIH", "Pachmo", "Palu", "Pejuwa", "Petko", "Pindra", "Purnapani", "Rahawan", "Rajderwa", "Rangamati", "Rohidih", "Rola", "SARHACHIA", "SASBEDA EAST", "SASBEDA WEST", "Saram (CT)", "Sawai", "Seheda", "Semarbera", "Siari", "Singpur", "Tenudam-Cum-Kathhara (CT)", "Tikahara", "Tilaiya", "Tirla", "Tiskopi", "Tisri", "Tithi", "Tuiyo", "Tulbul", "Tusko", "Tutijharna", "Uda", "pipradih", "saram west", "swang north", "swang south"], "Jaridih": ["Ara Saram", "Araju", "Araldih", "BANDH SOUTH", "Bahadurpur", "Bakaspura", "Balrampur", "Banchas", "Bandh Dih (CT)", "Baradih", "Baramasia", "Beldih", "Bharu", "Bhaski", "Birsaram", "Chilgora", "Gaichhana", "Gangjori", "Ganjhandi", "Garke", "Gopalpur", "Gopinath Pur", "Hanrhuro", "Haridih Hardi", "Jena (CT)", "Jogidih", "Kalyanpur", "Kamlapur", "Kashidih", "Kenduadih", "Khutri", "Kumhardih", "Lipu", "Manjhidih", "Nutandih", "Parsadih Tola", "Pathria", "Pengikudar", "Roria", "Saraibinda", "Sundro", "TANTARI NORTH", "TONDRA", "Tanr Balidih (CT)", "Tanr Mohanpur", "Tantri", "Thakurtanr", "Tilaiya", "Torra", "Totadih", "Tupkadih Tola"], "Kasmar": ["Astabera", "Bagda", "Bagiari", "Barai Khurd", "Baraikala", "Basria", "Bemrotand", "Bendotanr", "Bhawanipur", "Bhursatand", "Chainpur", "Chandipur", "Chawda", "Choli", "Dabhadih", "Dantoo", "Dhadhkia", "Dumarkudar", "Durgapur", "Garri", "Goriakudar", "Gumanjara", "Hanslata", "Harnad", "Hisim", "Jamhar", "Jamkudar", "Jharmunga", "Jumra", "Kairakudar", "Kamlapur", "Karkattakala", "Karkattakhud", "Karma", "Kasmar", "Kedla", "Khaira Chatar", "Khudibeda", "Khunta", "Kotogda", "Kurko", "Lodkiari", "Madhukar Pur", "Manjura", "Mayapur", "Medha", "Merombara", "Mochro", "Mungo", "Murhulsudi", "Nawadih", "Ormo", "Pakribandh", "Pari", "Pipradih", "Pirgul", "Ponda", "Raghunathpur", "Rangamati", "Silisaram", "Singhpur", "Sonhar", "Sonpura", "Surjudih", "Tangtona", "Telmunga", "Tironala", "Udaimara"], "Nawadih": ["AHARDIH", "Ahardih", "Amjhar", "Argamno", "BIRNI ANSH", "BRADIH ANSH", "Bansi", "Baradih", "Barai", "Baridih", "Barki Kuri", "Belargaraha", "Bhalmara", "Bhandar Kudar", "Bhandra (CT)", "Bhawani", "Birni", "Bodro", "Burgara", "Chapri", "Chepro", "Chhotki-Kuri", "Chirudih", "Dahiari", "Dalkiro", "Degagarha", "Dhamni", "Dhawatanr", "Galudih", "Ghosko", "Goladih", "Goniatu", "Gormara", "Gunjardih", "Harladih", "Junodih", "Juramana", "Kachho", "Kanchanpur", "Kanjkiro", "Kanjkiro Ans", "Katghara", "Kausi", "Kesgara", "Khaiyo Khar", "Kharpito", "Khunta", "Kimbu Jharia", "Koklodih", "Kothi", "Kujubera", "Kurpania", "Lahia", "Lembudih", "Mahuatanr", "Mochro", "Mongo Rangamati", "Mungo", "Narainpur", "Nawadih", "PALAMU ANSH", "Palamu", "Parasbani", "Penk", "Pilpilo", "Pipradih", "Pokhria", "Potso", "Saharia", "Sarubera", "Sundro", "Surhi", "Taratanr", "Tengnachunwa", "birni ansh", "bodro ansh", "prasbani ansh"], "Peterwar": ["Achaiya", "Ambadih", "Angwali", "Arari", "Arjua", "Baghjobra", "Banga", "Basaria", "Bhulan Khetko", "Bundu", "Chalkari", "Champi", "Chandarpura", "Chando", "Chargi", "Chatugara", "Chipudag", "DHARWATAND", "Darid", "Etke", "Gaga", "Gagi", "Garri", "Harmita", "Jabra", "Jabunal", "Jaruatanr", "Jhirki", "Jhujhko", "Kajrum", "Katamkuli", "Katarbera", "Keswari", "Kherho", "Khetko", "Khurdchando", "Koh", "Korarma", "Lepo", "Lukuiya", "Mayapur", "Merudaru", "Mirzapur", "Munga Sarla Alias Bhurhangor", "Nawadih", "Obra", "Ordana", "PICHADI SOUTH", "Patki", "Petarbar", "Phutkadih", "Pichhri", "Ponrdag", "Raghubahiar", "Rangamati", "Rohar", "Rukam", "Sadma Kalan", "Sadma Khurd", "Samlata", "Sarla Khurdalias Jaradih", "Takaha", "Ulgara", "Utasara", "tenughat"]}