{"Beerpur": ["Beerpur", "Cherlapalli", "Kammunur", "Kandlapalli", "Kolvai", "Mangela", "Narsimlapalli", "Rangasagar", "Rekulapalle", "Thalladharmaram", "Thungur"], "Buggaram": ["Beersani", "Buggaram", "Chinnapur", "Gangapur", "Gopulapuram", "Maddunur", "Shakalla", "Sirikonda", "Velgonda", "Yashwantharaopet"], "Dharmapuri": ["Arepalli", "Dharmapuri", "Donthapur", "Donur", "Jaina", "Kamalapur", "Maggidi", "Nagaram", "Nerella", "Rajaram", "Rayapatnam", "Sirivanchakota", "Stambampalle", "Theegala Dharmaram", "Thimmapur", "Thummenala"], "Gollapalli": ["Abbapur", "Aggimalla", "Atmakur", "Battubuttamrajapalli", "Bheemraj Palli", "Bonkur", "Chandoli", "Chilvakodur", "Datnur", "Gollapalli", "Gunjapadugu", "Ibrahim Nagar", "Israjpalli", "Lothunur", "Raghavapatnam", "Rapalle", "Thirmalapur", "Vengalapur", "Venugumatla"], "Ibrahimpatnam": ["Ammakkapet", "Bandalingapur", "Bardipur", "Dabba", "Erdandi", "Errapur", "Fakir Kondapur", "Godur", "Ibrahimpatnam", "KOJAN KOTHUR", "Kamala Nagar", "Komatikondapur", "Maidpalle (W)", "Mularampur", "Rajeswara Rao Pet", "Thimmapur", "Varshakonda", "Vemulakurthi", "Yamapur"], "Jagitial": ["Dharur", "Jagitial", "Mothe", "Tippannapet"], "Jagitial Rural": ["Anantharam", "Anthargaon", "Chelgal", "Dharmaram", "Gullapeta", "Habsipur", "Jabithapur", "Kalleda", "Kandlapalli", "Kannapur", "Laxmipuram", "Morapalli", "Narsingapur", "Polasa", "Porandla", "Somanpalli", "Thakkallapalle", "Thatipalli", "Thimmapur", "Veldurti"], "Kathlapur": ["Ambaripet", "Bhushanrao Peta", "Bommena", "Chinthakunta", "Dulur", "Dumpeta", "Gambhirpur", "Ippapalle", "Kalikota", "Kathlapur", "Naga Mallappakunta", "Ootpalle", "Peggerla", "Posanipeta", "Potharam", "Sirkonda", "Thakkallapalle", "Thandriyal", "Thurthi"], "Kodimial": ["Cheppial", "Gourapur", "Kodimial", "Konapur", "Kondapur", "Nachupalle", "Nallagonda", "Namilikonda", "Potharam", "Pudur", "Ramsagar", "Sanivarampeta", "Surampeta", "Thippaipalle", "Thiramalapur"], "Korutla": ["Ailapur", "Chinnametpalle", "Gumlapur", "Joganpalli", "Kallur", "Madhapur", "Mohanrao Pet", "Nagulpet", "Paidimadugu", "Peddapur", "Sangem", "Venkatapur", "Yekinpur", "Yusufnagar"], "Mallapur": ["Adavimadhapur", "Chittapur", "Damarajapalli", "Dharmaram", "Gorrepalli", "Gundampalli", "Indira Nagar", "Laxmipur", "Mallapur", "Mogalpet", "Muthyampet", "Nadukuda", "Obulapur", "Raghavapeta", "Ramdaspeta", "Regunta", "Sangem", "Sataram", "Sirpur", "Sri Rampur", "Valgonda", "Vempalli Venkatraopet"], "Mallial": ["Balwanthapur", "Gorregundam", "Maddutla", "Mallial", "Manala", "Muthyampeta", "Myadampalle", "Nookapalle", "Obulapur", "Potharam", "Rajaram", "Rampur", "Sarvapur", "Thakkallapalle", "Thatipalle"], "Medipalli": ["Bheemaram", "Dammannapeta", "Govindaram", "Kacharam", "Kalvakota", "Katlakunta", "Kondapur", "Lingampeta", "Machapur", "Mannnegudem", "Medipalle", "Pasnoor", "Pormalla", "Raghojipeta", "Rangapur", "Thombarao Peta", "Vallampalle", "Venkataraopeta", "Voddedu"], "Metpalli": ["Atmakur", "Chowlamaddi", "Jaggasagar", "Kondrikarla", "Masaipet", "Metlachittapur", "Ramalachakkapet", "Ramchandrampet", "Rangarao Pet", "Vellulla", "Vempet", "Venkatraopet", "Vittampet"], "Pegadapalli": ["Aithupalli", "Aravelli", "Bathkepalli", "Divikonda", "Keesulatapalli", "Laxmipur", "Legalamarri", "Lingapur", "Namapur", "Nancherla", "Nandagiri", "Narsimhunipeta", "Pegadapalli", "Thirmalapuram", "Vengalaipet", "Yellapur"], "Raikal": ["Allipur", "Alur", "Bhoopathipur", "Bornapalle", "Chintalur", "Devanpalle", "Dharmajipet", "Itkyal", "Katkapur", "Kistampet", "Kummaripalle", "Mahitapur", "Mootapalle", "Oddelingapur", "Raikal", "Ramajipet", "Tatlavai", "Uppumadige", "Vasthapur", "Veerapur"], "Sarangapur": ["Arpapalli", "Battapalli", "Ganeshpalli", "Komanpalle", "Konapur", "Lachakkapet", "Laxmidevipalle", "Mothinagar", "Nagunur", "Pembetla", "Potharam", "Rangapet", "Rechapalli", "Sarangapur"], "Velgatur": ["Ambaripet", "Chegyam", "Endapalli", "Godishelpet", "Gullakota", "Jagdevpet", "Kapparaopet", "Kishanraopet", "Kondapur", "Kothapet", "Mukkatraopet", "Muthunur", "Padkal", "Paidipalli", "Pathagudur", "Ramnur", "Sakapuram", "Sankenapalle", "Shanabanda", "Suraram", "Velgatur"]}