{"Ahore": ["Agwari", "Ahore (CT)", "Aipura", "Ajeetpura", "Akora Padar", "Alawa (A)", "Alawa (B)", "Alawa (C)", "Badanwari", "Bagoonda", "Bagotra", "Bala", "Bankli", "Baori", "Barwan", "Beechhawari", "Beejli", "Bhadrajoon", "Bhagli Purohitan", "Bhainswara", "Bhavrani", "Bhooti", "Bhorda", "Bithura", "Bokra", "Budtara", "Chandrai", "Charli", "Chawarcha", "Chawrda", "Cheeparwara", "Chhangari", "Choonda", "Dayalpura I", "Dayalpura Ii", "Debawas", "Dechhoo", "Devgarh", "Devki", "Dodiyali", "Doodiya", "Gangawa", "Ghana", "Godan", "Goindla", "Gura Balotan", "Gura Indrapura", "Gura Rama", "Hanwant Garh", "Hariyali", "Harjee", "Jaitpura", "Jogawa", "Jogni Khera", "Jora", "Kalora Padar", "Kamba", "Kaniwara", "Kawla", "Kawrada", "Keral", "Khambi", "Khara", "Khera Dhanari", "Khera Sanwri", "Khera Sooliya", "Kishangarh", "Korana", "Kotra", "Kuara", "Kuarda", "Kundli", "Madri", "Maheshpura", "Malgarh", "Malpura", "Mandla", "Manpura", "Meethri", "Mohiwara", "Moolewa", "Mori Tokariya", "Moroo", "Motisari", "Narwana", "Naya Rama", "Neelkanth", "Nimbla", "Norwa", "Nosra", "Nosra ki dhani", "Odwara", "Oon", "Pachanawa", "Padarli", "Palasiya", "Palasiya Khurd", "Panchota", "Pandgara", "Panwa", "Paota", "Peeparla Ki Dhani", "Pratap Garh", "Raithal", "Rajanwari", "Rama", "Rasiyawas", "Rasiyawas Khurd", "Ratanara", "Ratanpura", "Rewra Kalan", "Rodala", "Rundmal Ki Dhani", "Samooja", "Sandan", "Sankarna", "Sanwara", "Sapni", "Sarana", "Sarupura", "Sedariya Balotan", "Sedariya Kupawatan", "Selri", "Shankhwali", "Sugaliya Balotan", "Sugaliya Jodha", "Sugaliya Sindhlan", "Tarwara", "Thanwala", "Thoomba", "Thoomba Ka Goliya", "Tormi", "Ukarda", "Ummaidpur", "Valdara", "Varni", "Vedana", "Vedana Khurd", "Vedia"], "Bagora": ["Arnoo", "Bagawas", "Bagora", "Bagoti", "Bali", "Bhalni", "Bichhawari", "Bijaliya", "Chainpura", "Chak Jeran", "Chhajala", "Dabli Rathaoran", "Daman", "Deoda Ka Goliya", "Dhumbariya", "Doongarwa", "Gaonri", "Goojarwara", "Hapu Ki Dhani", "Jaisawas", "Jaitoo", "Janiyon Ki Dhani", "Jeran", "Kaleti", "Kawtara", "Kharwa", "Kherapuriya", "Khokha", "Kooka", "Kori Dhavecha", "Kura Dhavecha", "Lakhni", "Loombaram Bata Ki Dhani", "Loonawas", "Maiya Ki Dhani", "Meda Brahmnan", "Meerganj", "Meerpura", "Mindawas", "Morseem", "Nai Bali Ka Goliya", "Naibali", "Nandiya", "Narsana", "Nawapura Dhavecha", "Naya Chainpura", "Naya Morseem", "Pata Ki Dhani", "Rah", "Rangala", "Rauta", "Rupa Ki Dhani", "Sewari", "Sobrawas", "Vada Bharvi", "Vada Naya", "Vatera", "Vishnu Nagar"], "Bhinmal": ["Bhagal Bhim", "Bhagal Sephta", "Bheempura", "Bhinmal (Rural)", "Borta", "Chak Chandpan", "Dantiwas", "Daspan", "Dedaru", "Ghaseri", "Jogau", "Joojani", "Kerwala", "Khera Borta", "Kora", "Kot Kasta", "Kushlapura", "Ledarmer", "Narta", "Nasoli", "Navapura Chaupawatan", "Nimbawas", "Nimbora", "Nohra", "Phagotra", "Punasa", "Ruchiyar", "Sariyana", "Sarthala", "Than Mataji", "Thobau", "Vanu Ki Dhani", "Viyo Ka Golia"], "Chitalwana": ["Agrawa", "Ahmadkot", "Akoli", "Akoriya", "Amarpura", "Amba Ka Goliya", "Amli", "Ankhol", "Arwa", "Bagli", "Bagsari", "Balera", "Barsal Ki Beri", "Bediya Goliya", "Bhadoo & Goyton Ki Dhani", "Bhadroon", "Bhalaiyan", "Bhatki", "Bhatwas", "Bhawatra", "Bheemgura", "Bhimgurha Bhata", "Bhinchron Ki Dhani", "Bhootel", "Borli", "Chain Nagar", "Chamunda Nagar", "Charneem", "Chimra", "Chitalwana", "Dabal", "Dawal", "Dediya Vanga", "Dela", "Deora", "Devpura", "Dhaneriya", "Dharnawas", "Dheengpura", "Doongri", "Doothwa", "GIRDAR DHORA", "Galifa", "Godaron Ki Dhani (Hanumanji Ka Sthan)", "Gomi", "Hadecha", "Hali Bao", "Hanumanpura", "Hanuwantpura", "Haripurahema Ki Dhani", "Hazipur", "Hema Gura", "Hidwara", "Hoti Gaon", "Isharwal Goliya", "Isrol", "Itada", "JETESHVAR", "Jagdamba Nagar", "Jalberi", "Janguo Nagar", "Janipura", "Janvi", "Jaton Ka Goliya", "Jhab", "Jhotra", "Jodhawas", "Joradar", "K.R.Bandha Kua", "Kachhela", "Kagoda", "Kalji Ki Beri", "Keriya", "Kesoori", "Khamrai", "Khanpur", "Khasarvi", "Khejariyali", "Khirodi", "Koliyon Ki Garhi", "Koobiya", "Kukdeeya", "Kundaki", "LOTESHVAR", "Lalasar", "Lalpura", "Madaniyon Ki Dhani", "Madhopura", "Mailabas Charnan", "Mailawas Gusaiyan", "Malasar", "Malipara", "Malipura", "Malwa Nagar", "Malwara", "Mandali", "Manohar", "Martawa", "Marwari Kalbiyon Ka Goliya", "Medha", "Meghawa", "Mooli", "Naiyon Ki Dhani", "Naldhara", "Narali", "Narayanpura", "Nareshwar", "Nayawas Ranodar", "Nimbaj", "Nimbau", "PURANAGAR", "Padaradi", "Padardi", "Parawa", "Pawta", "Phogarwa", "Pratapnagar", "Raipuriya", "Ramdeo Nagar", "Rampura", "Rankhar", "Ranodar", "Ratanpura", "Rataura", "Ridiya Dhora", "Ridka", "SAKURGARH", "SHIVSANKAR NAGAR", "Sahu & Daukiyaon Ki Dhani", "Saili", "Sangarwa", "Sankariya", "Sarnawas", "Sayar Ka Koseeta", "Sayra", "Sensawa", "Shakti Nagar", "Sheraniyon Ki Dhani", "Shivgarh", "Shivpura", "Siloosan", "Sipaiyon Ki Dhani", "Siwara", "Siyako & Rado Ki Dhani", "Soonthri", "Sujan Nagar", "Sujanpura", "Sunta Koi", "Surachand", "Takhatgarh", "Tanpi", "Tatra", "Tembi", "Tetrol Rathoran", "Umarkot", "Vamal", "Vapa", "Varanpuri", "Varanwa", "Vediya", "Veerawa", "Vishanpur"], "Jalor": ["Adwara", "Akoli", "Alasan", "Anwloj", "Bagra", "Bakra", "Bakraroad", "Balwara", "Basan", "Beebalsar", "Berath", "Bhagli Sindhlan", "Bhetala", "Bishangarh", "Chak Samatipura", "Chandana", "Chhipi", "Choora", "Dakatara", "Dangara", "Deldari", "Devda", "Dewara", "Dhanpur", "Dhawala", "Digaon", "Doodsi", "Elana", "Jalor 'B' (Rural)", "Kalapura", "Kandar", "Katarasan", "Keshwana", "Khanpur", "Kolar", "Kuaber", "Leta", "Madalpura", "Maheshpura", "Mandwala", "Margaon", "Mauk", "Maylawas", "Meda Uparla", "Medanichla", "Mudi", "Nabi", "Nagni", "Narnawas", "Narpara", "Narsana", "Naya Narnawas", "Nimblana", "Noon", "Paharpura", "Pijopura", "Ranchhor Nagar", "Raniwara", "Ratunja", "Raypuriya", "Rewat", "Samati Pura", "Sanphara", "Santhoo", "Sarat", "Sardargarh", "Siwna", "Siyana", "Sumergarh", "Tadwa", "Takhtpura", "Teekhi", "Thalunda", "Ummedabad"], "Jaswantpura": ["Ajbar", "Ambatri", "Bara Bhawji", "Basra Dhanji", "Beethan", "Betarna", "Bhadarda", "Bharoori", "Bhootwas", "Bikanwas", "Boogaon", "Chak Chandna", "Chandna", "Chandoor", "Chekla", "Dantlawas", "Delwara", "Derdi", "Dhanpura", "Dhansa", "Dorda", "Gajapura 1/3", "Gajapura 2/3", "Gajipura", "Gola", "Golana", "Jaswant Pura", "Jawiya", "Jeetpura", "Jhak", "Jodwara", "Kalapura", "Karloo", "Keebla", "Khanda Deol", "Khanpur", "Kodita", "Kolar", "Kotra", "Loor", "Malpura", "Mandhar", "Mandoli", "Manoharji Ka Bas", "Modra", "Modra Ki Dhani", "Mudtara Sili", "Munthla Kaba", "Padar", "Paharpura", "Panseri", "Pawli", "Pawti", "Phaidani", "Pooran", "Punang Kalan", "Punang Khurd", "Raji Ka Bas", "Rajpura", "Ramseen", "Ratpura", "Rota", "Sawidar", "Seekwara", "Serna", "Shivgarh", "Sindhara", "Somta", "Tatol", "Tawab", "Thoor", "Uchmat", "Vishnoiyon Ka Goliya", "Warka Goga"], "Raniwara": ["ANADPURA", "Adapura", "Adarwara", "Ajodar", "Akhrad", "Alri", "Amarapura", "BHAKHARI DUNGRI", "BHAKTO KA WAS", "Bamanwara", "Bargaon", "Basra Bhoja", "Bhanwariya", "Bhapri", "Bhateep", "Bhatwas", "Bilar", "Chandpura", "Chara", "Charanwas", "Chatwara", "Chimangarh", "Chirpatiya", "Chitrodi", "Dadoki", "Daipur", "Dantwara", "Daulatpura", "Devpura", "Dhamseen", "Dhanol", "Dhanwara", "Dhuliya", "Digaon", "Dodwadiya", "Doodhwat", "Doongri", "Fatapura", "Gang", "Golwara", "Harshwara", "Heerpura", "Jakhri", "Jalera Kalan", "Jalera Khurd", "Jetpura", "Jorwas", "Kagmala", "Karda", "Karwara", "Ker", "Khakhariya", "Khera Sariyana", "Kherakuri", "Kori Chaupawatan", "Korka", "Kot Ki Dhani", "Kotra", "Kura", "Lakhawas", "Lalpura", "Maitriwara", "Malwara", "Mandardi", "Maroowara", "Medak Kalan", "Medak Khurd", "Mera", "Mokhampura", "Mokhatara", "Narayan Nagar", "Opa Ki Dhani", "Pal", "Parawi", "Peethapura", "Rampura", "Raniwara Kalan", "Raniwara Khurd", "Ratanpur", "Roda", "Ropsi", "Rupawati Kalan", "Rupawati Khurd", "Samrani", "Santroo", "Sanwlawas", "Sewadiya", "Sewara", "Silasan", "Singawas", "Surajwara", "Taveedar", "Tejawas", "Vada", "Vadal", "Vadlu", "Vagatapura", "Vandhar", "Varetha"], "Sanchore": ["Achalpur", "Agar", "Amarpura", "Arnay", "Ashapura", "Balana", "Bali Khera", "Bank", "Bapunagar", "Bari", "Barsam", "Bawarla", "Bhadroona", "Bhalani Sohuon Ki Dhani", "Bharkua", "Bharwal", "Bhawatra Jor@Sardarpura", "Bhura Ki Dhani", "Bhuwana", "Bichhawari", "Bijrol Goliya", "Bijrol Khera", "CHOURA KI DHANI", "Chaura", "Chhajara", "Choudhariyon Ka Goliya", "DUNGRO KA GOLIYA", "Dadhoora", "Dadoosan", "Dangra", "Danta", "Dantiya", "Dedwa", "Dedwa Khurd", "Dhamana", "Dhanta", "Dhoorwa", "Dugawa", "Gangasar", "Gardali", "Gena Ka Goliya", "Golasan", "Gundav", "Hadetar", "Hanumangarh", "Hanwant Nagar", "Haripura Neno Ka Was", "Hariyali", "Jaisla", "Jajoosan", "Jakhal", "Jambheshwar Pura", "Jelatra", "Jerol", "Jiva Ka Goliya", "Kabooli Ki Dhani", "Kailash Nagar", "Kalupura", "Kamalpura", "Kantol", "Karawari", "Karola", "Kervi", "Khaprol Ki Dhani", "Khara", "Kilawa", "Kiloopiya", "Kod", "Kola Rebariyon Ki Dhani", "Kura", "Lachhiwar", "Lachhiwar Ka Goliya", "Lachhri", "Lalnagar", "Lalpur", "Liyadra", "Looniyasar", "MAKHUPURA", "Maliyon Ka Goliya", "Maru Khera", "Meda Jageer", "Meerpura", "Nageshwar Nagar", "Nagolri", "Nainol", "Narayan Pura", "Neliya", "Paharpura", "Paladar", "Palri Deoran", "Palri Solankiyan", "Pamana", "Panchla", "Pathmeda", "Phalna", "Prahlad Nagar", "Prajapati Nagar", "Pratapgarh", "Pratappura", "Prithvimera", "Pur", "Raghunathpura", "Rajeev Nagar", "Rajeshwar Pura", "Rajpura", "Rawatsar", "Ruda Ka Goliya", "SANCHORE", "Sankar", "Sarnau", "Sarwana", "Sediya", "Shivamnagar", "Shivnagar", "Siddheshwar", "Siloo", "Siyagaon", "Surawa", "Suthana", "Suthron Ka Goliya", "TULSANI KI DHANI", "Teetop", "Tetrol Sunakhera", "Valaji Ki Dhani", "Vandeo", "Vasan Chauhan", "Vasan Deoran", "Virol Bari", "Virol Chhoti", "Vishnu Nagar", "Vishnu gad", "Vodha"], "Sayla": ["Akwa", "Alwara", "Asana", "Babtara", "Bhundwa", "Borwara", "Chaurau", "Chonchawan", "Dabli", "Dadal", "Dahiva", "Deta Kalan", "Deta Khurd", "Dhanani", "Doodhwa", "Harmoo", "Jalampura", "Jeewana", "Jor Virana", "Kharal", "Khari", "Khera Gangawa", "Khetlawas", "Komta", "Lodrau", "Lumba Ki Dhani", "MUGLONIYO KI DHANI", "Mandakwana", "Mengalwa", "Mokni Khera", "Narwara", "Otwala", "Pantheri", "Posana", "Punawas", "Punrau", "Raghunathpura", "Rewatra", "Rohinwara", "Sajanpura", "Sangana", "Sayla", "Sirana", "Surana", "Taliyana", "Teja Ki Beri", "Thalwar", "Tilora", "Tura", "Unri", "Virana", "Vishala", "Walera"]}