{"Atholi (Paddar)": ["Afani", "Atholi", "Batwas", "Chag", "Chittoh", "Gadh", "Gulabgarh", "Ishtyari", "Jaar", "Kabban", "Kadail", "Kidroo", "Kundal", "Laas", "Laddar", "Ligri", "Loondi", "Masoo", "Matti", "Muthal", "Ongai", "Palali", "Pander", "Sazar", "Sohal", "Tiyari", "Tun"], "Bounjwah": ["Binoon", "Jawalapur", "Jirwar", "Kewa", "Kither", "Mori", "Nali", "Patnazi", "Tipri"], "Chhatroo": ["Chhatroo", "Chingam", "Dichhad", "Inderwal", "Udil Gujran"], "Dachhan": ["Chicha", "Janakpur", "Loharna", "Lopara", "Sounder"], "Drabshalla": ["Akarhing", "Badhat", "Balgran", "Bathkoot", "Bathna", "Bhandera", "Bharoti", "Brashila", "Bugrana", "Chalasoo", "Chamoti", "Dhar Saroor", "Dharbhangar", "Dugga", "Gadh", "Hadar", "Haloor", "Joshana", "Kalchanda", "Kawarthara", "Khori", "Kukerwas", "Kutal", "Lass", "Londri", "Malai", "Mandir", "Nagbathna", "Niju", "Ohli", "Prashmoola", "Salana", "Sangna", "Shandri", "Sharoti", "Tatani"], "Kishtwar": ["Agral", "Anjole", "Bhandarkoot", "Chandali", "Cherji", "Dharbadan", "Dool", "Drab", "Feller", "Ghan", "Hidyal", "Janwas", "Karool", "Keshwan", "Kishtwar", "Kwartanji", "Lach Dayaram", "Lach Khazana", "Lava", "Matta", "Pakalan", "Palmar", "Pochhal", "Pora", "Sarawan", "Sirgwari", "Trigam"], "Machail": ["Chasoti", "Hamori", "Hango", "Losain", "Machail"], "Marwah": ["Changer", "Deharna", "Dehrai", "Hanzal", "Nowapachi", "Nowgam", "Pethgam", "Qaderna", "Renai", "Teller", "Yourdoo"], "Mughalmaidan": ["Bhata", "Dhar", "Drubeel", "Horna", "Kuchhal", "Mulchiter", "Rahalthal", "Sigdi", "Tagood"], "Nagseni": ["Ajna", "Bhagna", "Bhatan", "Chandna", "Chicha", "Chingnana", "Dichla", "Dimji", "Galhar Bhata", "Piyas", "Semna Bhata"], "Warwan": ["Afti", "Basmina", "Brayan", "Choidraman", "Gumri", "Inshan", "Margi", "Mulwarwan", "Mungli", "Rekenwas", "Sukhnai"]}