{"Bellampally": ["Akenipalle", "Ankusam", "Batwanpalle", "Budha Kalan (R)", "Budha Khurd (R)", "Chakepalle", "Chandravelli", "Dugnepalle", "Gurjal (R) @ Talla Gurjal", "Kannal (R)", "Perkapalle", "Rangapet"], "Bheemaram": ["Ankushapur", "Arepalle", "Arkepalle", "Bhimaram", "Burugupalle", "Dampur", "Kothapalle", "Maddikal", "Polampalle", "Pothanpalle", "Reddipalle", "Vellapalle"], "Bheemini": ["Akkalapalle", "Bhimini", "Bitturpalle", "Chinna Thimmapur", "Chinnagudipet", "Kamalapur", "Karjibheempur", "Keslapur", "Laxmipur", "Mallidi", "Pedda Thimmapur", "Peddagudipet", "Peddapeta", "Pothepalle", "Rajaram", "Rampur", "Ramraopeta", "Thangallapalle", "Veegaon", "Venkatapur", "Wadal"], "Chennur": ["Adiwarpet", "Akkapalle", "Amudalpalle", "Angarajpalle", "Asnad", "Beervelli", "Bhamraopet", "Buddaram", "Chakepalle", "Chennur (CT)", "Chintapalle", "Dugnepalle", "Gangaram", "Guddirampur", "Kachanpalle", "Kannepalle", "Kathersala", "Khambojipet", "Kistampet", "Kommera", "Konampet", "Lingampalle", "Nagapur", "Narasakkapet", "Narayanpur", "Pokkur", "Ponnaram", "Raipet", "Sankaram", "Shivalingapur", "Somanpalle", "Suddal", "Sundersala", "Yellakkapet"], "Dandepally": ["Allipur", "Andugulpet", "Bikkanguda", "Chintapalle", "Dandepalle", "Dharmaraopet", "Dwaraka", "Gudam", "Gurrevu", "Jaidapet", "Kamepalle", "Karvichelma", "Kasipet", "Kondapur", "Kundelapahad", "Laxmikantapur", "Lingapur", "Makulpet", "Mamidipalle", "Medaripet", "Mutyampet", "Nagasamudram", "Nambal", "Narsapur", "Peddapet", "Rebbenpalle", "Rollpahad", "Tallapet", "Tanimadugu", "Velganoor", "Venkatapur"], "Hajipur": ["Chandanapur", "Donabanda", "Gadhpur", "Gudipet", "Hajipur", "Hussainsagar", "Karnamamidi", "Kondapur", "Kondepalle", "Kothapalle", "Mulkalla", "Nagaram", "Namnur", "Padthenpalle", "Peddampet", "Pochammapad", "Rapalle", "Ryali", "Subbapalle", "Vempalle"], "Jaipur": ["Bejjal", "Gangipalle", "Gopalpur", "Indaram", "Jaipur", "Kachanpalle", "Kankur", "Kistapur", "Kundaram", "Maddikunta", "Maddulapalle", "Mittapalle", "Narasingapuram", "Narva", "Pegadapalle", "Pownur", "Ramaraopet", "Rommipur", "Shetpalle", "Shivvaram", "Tekumatla", "Velal", "Yelkanti"], "Jannaram": ["Badampalle", "Bommena", "Chintaguda", "Dharmaram", "Dongapalle", "Indhanpalle", "Jannaram", "Juviguda", "Kalmadagu", "Kamanpalle", "Kawal", "Kishtapur", "Kothapet", "Malyal", "Marriguda", "Murimadugu", "Narsingapur", "Paidpalle", "Papammaguda", "Ponakal", "Puttiguda", "Raindlaguda", "Rampur", "Singaraipet", "Thimmapur", "Venkatapur"], "Kannepally": ["Ankannapeta", "Babapur", "Chintapudi", "Dampur", "Gollaghat", "Jajjarvelly", "Jankapur", "Kannepalle", "Kothapalle", "Lingala", "Lingapur", "Madavelli", "Metpalle", "Motkupalle", "Muthapur", "Nagepalle", "Polampalle", "Rebbena", "Saligaon", "Shiknam", "Surjapur", "Tekulapalle", "Veerapur", "Yellaram"], "Kasipet": ["Chintaguda", "Devapur (CT)", "Dharmaraopet", "Gatrapalle", "Gurvapur", "Kankalapur", "Kasipet (CT)", "Kometichenu", "Kondapur", "Konur", "Kurreghad", "Malkepalle", "Muthempalle", "Pallamguda", "Peddampalle (R)", "Peddapur", "Rottepalle", "Sonapur", "Tirmalapur", "Varipet", "Venkatapur"], "Kotapally": ["Adkapalle", "Algaon", "Annaram", "Arjungutta", "Ayepalle", "Bopparam", "Borampalle", "Brahmanpalle", "Chintakunta", "Dewalwada", "Edagatta", "Edula Bandam", "Jangaon", "Kawarkothapalle", "Kollur", "Kondampet", "Kotapalle", "Lingannapet", "Mallampet", "Nagampet", "Nakkalpalle", "Pangadisomaram", "Parpalle", "Pinnaram", "Pullagaon", "Rajaram", "Rampur", "Rapanpalle", "Rawalpalle", "Sarvaipet", "Shankarpur", "Shetpalle", "Sirsa", "Supak", "Venchapalle", "Vesonvai", "Yerraipet"], "Luxettipet": ["Balraopet", "Challampet", "Chandram", "Dowdepalle", "Ellaram", "Gullakota", "Itkyal", "Jendavenkatapur", "Kothur", "Laxmipur", "Lingapur", "Luxettipet (CT)", "Mittapally", "Modela", "Patha Kommugudem", "Pothepalle", "Rangapet", "Talamalla", "Thimmapur", "Utukur", "Venkataraopet"], "Mancherial": ["Narsingapur", "Naspur (CT)", "Singapur (CT)", "Teegalpahad (CT)", "Thallapalle (CT)"], "Mandamarri": ["Amerwadi", "Andgulapet", "Chirrakunta", "Kyathampalle", "Kyathampalle (CT)", "Lemur", "Mamidighat", "Ponnaram", "Sarangapalle", "Thimmapur", "Venkatapur"], "Naspur": ["Naspur", "Seetarampalle (OG)", "Singapur", "Teegalpahad", "Thallapalle"], "Nennel": ["Avadam", "Bhadrapur", "Bhagirathipet", "Bodhapur", "Chinavenkatapur", "Chittapur", "Dammireddipet", "Ghanpur", "Gollapalle", "Gudipet", "Gundlasomaram", "Jangalpet", "Jhandavenkatapur", "Jogapur", "Khammampalle", "Kharji", "Konampet", "Kothur", "Kushenapalle", "Mailaram", "Mankapur", "Manneguda", "Metpalle", "Nandulapalle", "Nennal", "Pottiyal", "Puppulawanipet", "Singapur", "Sitanagar"], "Tandur": ["Abbapur", "Achalapur", "Ankepalle", "Annaram", "Balhanpur", "Boyapalle", "Chandrapalle", "Choutpalle", "Dwarakapur", "Gampalpalle", "Gopalnagar", "Kasipet", "Katherla", "Kistampet", "Kothapalle", "Madaram", "Madnapur", "Narsapur", "Pegadapalle", "Rampur", "Rechini", "Repallewada", "Tandur", "Venkaipalle"], "Vemanpally": ["Baddampalle", "Baddevelle", "Bommena", "Buyyaram", "Chamanpalle", "Dasnapur", "Gorlapalle", "Gudampet", "Gudepalle", "Jajulpet", "Jakkepalle", "Jilleda", "Kallampalle", "Kalmalpet", "Katepalle", "Kothapalle", "Kyathanpalle", "Maddulapalle", "Mamda", "Mukkidigudem", "Mulkalpet", "Nagaram", "Neelwai", "Oddugudem", "Racherla", "Rajaram", "Sumputum", "Suraram", "Upparlapahad", "Vemanpalle"]}