{"Dhoraji": ["Bhadajaliya", "Bhader", "Bhola", "Bholgamda", "Bhukhi", "Bhutvad", "Chhadvavadar", "Chhatrasa", "Chichod", "Dhoraji", "Fareni", "Hadmatiya", "Jamnavad", "Kalana", "Moti Marad", "Moti Parabdi", "Moti Vavdi", "Nagalkhada", "Nani Marad", "Nani Parabdi", "Nani Vavdi", "Patanvav", "Pipaliya", "Supedi", "Toraniya", "Udakiya", "Umarkot", "Vadodar", "Vegdi", "Velariya", "Zanzmer"], "Gondal": ["Ambardi", "Analgadh", "Anida", "Bandhiya", "Bandra", "Betavad", "Bhandariya", "Bharudi", "Bhojpara", "Bhunava", "Bildi", "Biliyala", "Charakhdi", "Chordi", "Dadva Hamirpara", "Daiya", "Daliya", "Derdi", "Devachadi", "Devla", "Dharala", "Dhudashiya", "Garnala", "Ghoghavadar", "Gomta", "Gondal", "Gundala", "Gundasara", "Hadamatala", "Hadmadiya", "Jamvali", "Kamadhiya", "Kamarkotda", "Kantoliya", "Karmal Kotda", "Keshvala", "Khambhalida", "Khandadhar", "Kolithad", "Lilakha", "Lunivav", "Mahika Mota", "Mahika Nana", "Mandankundla", "Masitala", "Mespar", "Meta Khambhaliya", "Mota Sakhpar", "Moti Khilori", "Moviya", "Mungavavdi", "Nagadka", "Nana Sakhpar", "Navagam", "Padavala", "Panchiyavadar", "Patidad", "Patiyali", "Patkhilori", "Pipaliya", "Ransiki", "Ravna", "Rib", "Ribda", "Rupavati", "Sajadiyali", "Shemla", "Shivrajgadh", "Shrinathgadh", "Sindhavadar", "Sultanpur", "Trakuda", "Umvada Mota", "Umvada Nana", "Vachhra", "Valadhari", "Vanthali", "Vasavad", "Vejagam", "Vekri", "Vinzivad", "Vorakotda"], "Jamkandorna": ["Adval", "Anchvad", "Balapar", "Bandhiya", "Bardiya", "Belda", "Boriya", "Charel", "Chavandi", "Chitravad", "Chitravad Pati", "Dadar", "Dadvi", "Dholidhar", "Dudhivadar", "Gundasari", "Hariyasan", "Ishvariya", "Jam Kandorna", "Jasapar", "Kanavadala", "Khajurda", "Khatli", "Khijadiya Moj", "Matravad Juna", "Matravad Nava", "Meghavad", "Mota Bhadra", "Padariya", "Pipaliya Agency", "Pipaliya Maljibhi", "Pipardi", "Rajpara", "Rampar", "Rangpar", "Raydi", "Rodhel", "Sajadiyali", "Sanala", "Satudad", "Sodvadar", "Taravda", "Tarkasar", "Thorala", "Thordi", "Ujala", "Vavdi"], "Jasdan": ["Adhiya", "Ambardi", "Ankadiya", "Atkot", "Bakhalvad", "Baldhoi", "Barvala", "Bhadla", "Bhadli", "Bhandariya", "Boghravadar", "Chitaliya", "Dahinsara", "Devpara", "Dodiyala", "Dolatpar", "Gadhadiya (Jam)", "Gadhadiya (Jas)", "Gadhala", "Godladhar", "Gokhlana", "Gundala Jam", "Hadmatiya khanda", "Ishvariya", "Jangvad", "Jasapar", "Jasdan", "Jivapar", "Juna Pipaliya", "Kaduka", "Kalasar", "Kamlapur", "Kanesara", "Kanpar", "Khadvavdi", "Kharachiya Jam", "Kothi", "Kundani", "Lilapur", "Madava", "Madhavipur", "Madhda", "Meghpar", "Nani Lakhavad", "Navagam", "Panchavada", "Parewala", "Polarpar", "Pratappur", "Raja Vadla Jam", "Rajavadla Jas", "Ramaliya", "Raningpar", "Ranjitgadh", "Ranparda", "Sanathali", "Shivrajpur", "Vadod", "Veraval Bhadla", "Veraval sanathali", "Virnagar", "Virpur", "Zundala"], "Jetpur": ["Akala", "Amarnagar", "Amrapar", "Arab Timbdi", "Bava Pipaliya", "Bheda Pipaliya", "Bordi Samadhiyala", "Champrajpur", "Charan Samadhiyala", "Charaniya", "Dedarva", "Derdi", "Devki Galol", "Haripar", "Jambudi", "Jepur", "Jetalsar (CT)", "Jetalsar (Junction)", "Jetpur", "Juni Sankali", "Kagvad", "Kerali", "Khajuri Gundala", "Kharachiya", "Khirsara", "Lunagara", "Lunagiri", "Mandlikpur", "Mevasa", "Monpar", "Mota Gundala", "Navagadh", "Navi Sankali", "Panchpipla", "Pedhla", "Pipalva", "Pithadiya", "Premgadh", "Rabarika", "Reshamdi Galol", "Rupavati", "Sardharpur", "Seluka", "Station Vavdi", "Thana Galol", "Thorala", "Umrali", "Vadasada", "Valadungra", "Virpur"], "Kotda Sangani": ["Ambaliala", "Anandpar", "Anida", "Ardoi", "Bagdadiya", "Bhadoi", "Bhadva", "Champabeda", "Detadiya", "Devaliya", "Hadamatala", "Juna Rajpipla", "Juni Mengani", "Kalambhdi", "Khareda", "Khokhri", "Kotda Sangani", "Manekvada", "Mota Mandava", "Nana Mandava", "Naranka", "Nava Rajpipla", "Navi Mengani", "Noghanchora", "Padavala", "Panchtalavda", "Pipaliya Karmal", "Piplana", "Rajgadh", "Rajpara", "Ramod", "Rampara", "Sandhavaya", "Satapar", "Shapur (CT)", "Shishak", "Soliya", "Thordi", "Vadipara", "Vadiya", "Veraval (CT)"], "Lodhika": ["Abhepar", "Balsar", "Chandli", "Chhapra", "Chibhda", "Devgam", "Devla", "Dholara", "Dhudiya Domda", "Haripar Pal", "Haripar Taravada", "Jashvantpur", "Jetakuba", "Kangashiyali", "Khambha", "Khirsara (Ranmalji)", "Kotha Pipaliya", "Laxmi Intala", "Lodhika", "Makhavad", "Metoda", "Motavada", "Nadhu Pipaliya", "Nagar Pipaliya", "Pal", "Pambhar Intala", "Pardi", "Pipaliya Pal", "Pipardi", "Rataiya", "Ratanpar", "Ravki", "Sanganva", "Taravada", "Und Khijadiya", "Vagudad", "Vajdi (Vad)", "Virva"], "Paddhari": ["Adbalka", "Amreli", "Baghi", "Bodi Ghodi", "Chanol Moti", "Chanol Nani", "Chanol Navi", "Chhelli Ghodi", "Dahisarda (Aji)", "Dahisarda Und", "Depaliya", "Dhokaliya", "Dhunana Gam", "Domda Bhayuna", "Dungarka", "Fatepar", "Gadhda", "Govindpar", "Hadmatiya", "Haripar", "Hidad", "Intala Nana", "Ishvariya", "Jhilariya", "Jivapar", "Jodhpar Chhala", "Kerala", "Khajurdi", "Khakhada Bela", "Khambhala", "Khamta", "Khandheri", "Khijadiya Mota", "Khijadiya Nana", "Khodapipar", "Khokhri", "Metoda", "Moviya", "Nanavada", "Naranka", "Nyara", "Paddhari (CT)", "Radad", "Rampar Mota", "Rampar Pati", "Rangpar", "Rojiya", "Rupavati", "Sagaliya Nana", "Sal Pipaliya", "Sarapdad", "Suvag", "Targhari", "Thoriyali", "Ukarda", "Vachli Ghodi", "Vanpari", "Visaman"], "RAJKOT EAST": ["RAJKOT", "THORALA"], "RAJKOT SOUTH": ["MAVDI"], "RAJKOT WEST": ["NANA MAUVA", "RAIYA"], "Rajkot": ["Amargadh", "Anandpar", "Anandpar (CT)", "Aniyala", "Badpar", "Bamanbore", "Barvan", "Bedi", "Bedi (OG)", "Bedla", "Bhangda", "Bhayasar", "Bhupgadh", "Chanchadiya", "Chitravav", "Deroi", "Dhamalpar", "Dhandhiya", "Dhandhni", "Dungarpar", "Fadadang", "Gadhka", "Garida", "Gavaridad", "Ghanteshvar (CT)", "Golida", "Gunda", "Gundala", "Hadala", "Hadmatiya (Bedi)", "Hadmatiya (Golida)", "Halenda", "Haripar", "Hirasar", "Hodthali", "Jaliya", "Jamgadh", "Jhiyana", "Jivapar (Bamanbore)", "Kagdadi", "Kalipat", "Kankot", "Kasturbadham", "Kathrota", "Kharachiya", "Kherdi", "Khijadiya", "Khokhadadad", "Khorana", "Kotharia (CT)", "Kothariya", "Kuchiyadad", "Kuvadva", "Lakhapar", "Lampasari", "Lodhida", "Lothada", "Madhapar (OG)", "Magharvada", "Mahika", "Makanpar", "Maliyasan", "Manharpur (OG)", "Mesvada", "Mota Mava (OG)", "Munjka (OG)", "Nagalpar", "Nakaravadi", "Navagam", "Navagam (Bamanbore)", "Padasan", "Para Pipaliya", "Parevala", "Pipaliya", "Rafala", "Rajgadh", "Ramnagar", "Rampara", "Rampara (Suliya)", "Rampara Beti", "Ranpar", "Ratanpar", "Ronki", "Sajadiali Lili", "Sajadiali Suki", "Samadhiyala", "Sanosara", "Sar", "Sardhar", "Satda", "Saypar", "Sokhada", "Targhadiya", "Thebachda", "Umrali", "Vadali", "Vajdi (Virda)", "Vajdi Gadh", "Vankvad", "Vavdi (OG)", "Vejagam", "Vijaynagar"], "Upleta": ["Arni", "BHAYAVADAR", "Bhankh", "Bhimora", "Charelia", "Chikhalia", "Dhank", "Dumiyani", "Gadha", "Gadhala", "Gadhethal", "Ganod", "Hadfodi", "Hariyasan", "Isra", "Jal", "Kalaria", "Kathrota", "Kerala", "Khakhi Jalia", "Kharachia", "Khirsara", "Kolki", "Kundhech", "Lath", "Makhiyala", "Mekhatimbi", "Meli Majethi", "Mervadar", "Mojira", "Murakhada", "Nagvadar", "Navapara", "Nilakha", "Padvala", "Paneli Moti", "Pransla", "Rabarika", "Rajpara", "Sajdiyali", "Samadhiyala", "Satvadi", "Sevantra", "Talgana", "Tanasva", "Timbadi Jam", "UPLETA", "Vadali", "Vadekhan", "Vadla", "Varjang Jalia"], "Vinchchiya": ["Ajmer", "Amrapur", "Asalpar", "Bandhali", "Belda", "Bhonyra", "Chhasiya", "Dadli", "Devdhari", "Dhedhuki", "Fulzar", "Goraiya", "Gundala (Jas)", "Hathasani", "Hingolgadh", "Janada", "Kandhevaliya", "Kansloliya", "Khadkana", "Kharachiya Jas", "Kotda", "Lalavadar", "Modhuka", "Mota Hadmatiya", "Mota Matra", "Moti Lakhavad", "Nana Matra", "Ori", "Patiyali", "Pipardi", "Revaniya", "Rupavati", "Samadhiyala", "Sanala", "Sanali", "Sartanpar", "Som Pipaliya", "Somalpar", "Thoriyali", "Vanala", "Vangadhara", "Veraval Bhadli", "Vinchhiya"]}