{"Banihal": ["Amkote", "Asher", "Bankoot", "Bohardar", "Chachal", "Chacknarwah", "Chaknarwah", "Chamalwas", "Chanjloo", "Chapnari", "Chareel", "Dannar", "Darshipora", "Devgole", "Doligam", "Gund Adulkote", "Gund Tethar", "Harwari", "Hinjhall", "Jagir Namdar", "Kaskoot", "Khairkote", "Kharpora", "Kralchihal", "Krawa", "Ladnihal", "Ladnihal Surranga", "Lamber", "Nagam", "Neel", "Nowgam", "Parihinder", "Phagow Nowkote", "Tajnihal", "Takia", "Tethar", "Zanihal"], "Batote": ["Barthal", "Batote", "Bendhere", "Chackwa", "Champa", "Chilla", "Dharalta", "Dharmound", "Dharshivgarh", "Kothri", "Ladwal", "Rakhjarog", "Sanasar", "Sanna", "Thopal", "Tringla"], "Gool": ["Ashmar", "Bandan", "Baralla", "Bhimdassa", "Chachwah", "Dachan", "Dalwah", "Dharam", "Dheeda", "Famrote", "Gagersool", "Goe", "Gool", "Gundi", "Haila", "Hara", "Ind", "Jaman", "Kalimasta", "Lower Dalwah", "Mahakund", "Monglogi", "Movelkote", "Paratmoola", "Salbalah", "Sangaldan", "Sarlibagi", "Seripura", "Surranda", "Thatharka", "Wanding"], "Khari": ["Bawa", "Buzla", "Khari", "Mahu", "Mangit", "Nachlana", "Sarachi", "Shagan", "Tranna", "Trigam", "Udhala"], "Pogal Paristan": ["Alinbass", "Baas Maligam", "Bangara", "Chakka", "Dhanmasta", "Hochak", "Khowra", "Kunda Khaas", "Maligam", "Narthyal", "Noora", "Panchal", "Paristan", "Phagmullah", "Pogal Khaas", "Ramsoo", "Sarbagni", "Senabathi", "Sujmatna", "Ukhral"], "Rajgarh": ["Deswal", "Dhandela", "Dharli", "Dramen", "Ghari", "Hillar", "Jhatgali", "Kumate", "Rajgarh", "Tanger"], "Ramban": ["Adhwa", "Badhole", "Bajmasta", "Balihote", "Banera", "Batli", "Bhatan", "Billawat", "Chander Kote", "Dalwas", "Damote", "Dandrath", "Dhar", "Digdole", "Dukson", "Duthan", "Gam", "Gandhari", "Gandhote", "Ganote", "Halla", "Harog", "Jawari", "Kabbi", "Kanga", "Kanthi", "Karma", "Kothi", "Kundi", "Kunfer", "Maitra", "Marog", "Nangal", "Neera", "Papria", "Pari", "Pernote", "Ramban", "Sawani", "Sencha", "Seri", "Sildhar", "Somber", "Tanger", "Tatarsoo", "Telli"]}