{"BHAWANIGARH": ["Akbarpur (103)", "Alo Arkh (38)", "Bakhopir (16)", "Bakhtra (17)", "Bakhtri (18)", "Balad Kalan (36)", "Balad Khurd (57)", "Balial (56)", "Basiarkh (97)", "Batriana (106)", "Bharo (24)", "Bhatiwal Kalan (53)", "Bhatiwal Khurd (54)", "Bhuraj (71)", "Bibar (21)", "Bibri (22)", "Bijalpur (101)", "Bir Mehsampur (227)", "Channo (69)", "Dehlewal (23)", "Dialgarh (38)", "Dittupur (229)", "Fatehgarh Bhadson (12)", "Fatehnagar Alias Munshiwala (29)", "Gehlan (44)", "Gharachon (108)", "Harditpura (34)", "Harkishanpura (47)", "Jhuneri (107)", "Jolian (13)", "Julan (233)", "Kakra (41)", "Kalajhar (28)", "Kapial (104)", "Kheri Chandwan (45)", "Kheri Gillan (27)", "Lakhewal (70)", "Majha (19)", "Majhi (20)", "Masani (30)", "Matran (59)", "Mehsampur (228)", "Nadampur (35)", "Nagra (109)", "Nakta (33)", "Nandgarh (231)", "Nandgarh Alias Thaman Singhwala (58)", "Naraingarh (98)", "Nurpura (26)", "Panjbiri (39)", "Panwan (14)", "Phaguwala (50)", "Phumanwal (32)", "Rai Singhwala (49)", "Rajpura (31)", "Ramgarh (99)", "Ramnagar Alias Ghumand Singhwala (46)", "Rampura (51)", "Rasulpur Chhanna (230)", "Retgarh (52)", "Roshanwala (48)", "Sajuma (56)", "Sakrodi (43)", "Sangatpura (42)", "Sangheri (105)", "Santokhpura (232)", "Shahpur (25)", "Turi (37)"], "DIRBA": ["Bagrol (127)", "Dewangarh Alias Kaimpur (116)", "Dhandial (157)", "Dhandoli Kalan (113)", "Dhandoli Khurd (111)", "Dharamgarh Chhanna (137)", "Dialgarh Jejian (123)", "Ghanaur Rajputa (125)", "Gujran (110)", "Harigarh (150)", "Janal (118)", "Kadar Nagar Alias Munshiwala (135)", "Kakuwala (146)", "Kamalpur (126)", "Karial (136)", "Khanal Kalan (122)", "Khanal Khurd (121)", "Khanpur Faqiran (102)", "Kheri Naga (115)", "Khetla (140)", "Ladbanjara Kalan (147)", "Ladbanjara Khurd (145)", "Nihalgarh (144)", "Rampura Gujran (117)", "Rattangarh Sidhran (139)", "Rogla (114)", "Samuran (134)", "Santpura (124)", "Shadi Hari (156)", "Shafipur Kalan (132)", "Shafipur Khurd (133)", "Sihal (131)", "Sullar (112)", "Toor Banjara (119)", "Ubha (148)"], "Dhuri": ["Alal (36)", "Alipur Khalsa (20)", "Babanpur (71)", "Badshahpur (42)", "Balamgarh (70)", "Balian (48)", "Bamal (65)", "Banbhori (73)", "Banganwali (89)", "Bararwal (92)", "Bari (29)", "Batuha (49)", "Belewal (74)", "Benra (95)", "Bhadalwadh (103)", "Bhagwanpura (13)", "Bhalwan (107)", "Bhasaur (72)", "Bhojowali (104)", "Bhullarheri (106)", "Buggra (56)", "Burj Gohra (82)", "Burj Seda (83)", "Changli (24)", "Cheema (84)", "Daulatpur (64)", "Dhadogal (76)", "Dhandiwal (46)", "Dhandra (99)", "Dhura (97)", "Dhuri (R) (94)", "Didargarh (39)", "Dohla (93)", "Fatehgarh (3)", "Ghanaur Kalan (67)", "Ghanaur Khurd (66)", "Ghanauri Kalan (43)", "Ghanauri Khurd (41)", "Gobindpura (14)", "Gurbaxpura (17)", "Harchandpur (98)", "Hassanpur (54)", "Herike (37)", "Ina Bajwa (32)", "Isra (78)", "Issapur (21)", "Issi (79)", "Jahangir (61)", "Jainpur (77)", "Jakhlan (100)", "Jati Majra (69)", "Kaheru (62)", "Kakarwal (60)", "Kalabula (40)", "Kaleran (23)", "Kandhargarh (185)", "Kanjla (52)", "Kanjli (51)", "Katron (46)", "Kaulseri (101)", "Kheri Chahalan (12)", "Kheri Jattan (81)", "Kheri Khurd (11)", "Kumbarwal (47)", "Ladda (58)", "Lohar Majra (80)", "Malu Majra (63)", "Manah (87)", "Manwala (96)", "Meerheri (102)", "Mehdudpur Urf Dugni (68)", "Mimsa (86)", "Mohamadpur (19)", "Mulowal (45)", "Natt (50)", "Palasaur (105)", "Patti Khalil (30)", "Pedni Kalan (59)", "Pharwahi (22)", "Punnawal (57)", "Qila Hakiman (53)", "Rajinder Puri (90)", "Rajo Majra (44)", "Ramgarh (27)", "Ramnagar Chhanna (28)", "Rangian (34)", "Ranike (55)", "Ruldu Singhwala (91)", "Rurgarh (25)", "Salempur (38)", "Samundgarh (85)", "Sherpur (31)", "Sherpur Sodhian (88)", "Sultanpur (35)", "Tibba (16)", "Wazirpur (18)"], "Lehra": ["Alampur (69)", "Alisher (70)", "Arkbas (64)", "Bakhora Kallan (77)", "Bakhora Khurd (76)", "Bhutal Kalan (61)", "Changliwala (54)", "Chotian (78)", "Chural Kalan (81)", "Chural Khurd (80)", "Daska (48)", "Fatehgarh (50)", "Gaga (67)", "Ghoranab (59)", "Gidrani (51)", "Gobindpura Jawarwala (72)", "Gurney (71)", "Haryau (49)", "Jhaloor (152)", "Kal Banjara (60)", "Kalia (79)", "Khai (65)", "Khandebad (62)", "Khokhar (55)", "Kotra Lehal (68)", "Ladal (52)", "Lehal Kalan (75)", "Lehal Khurd (74)", "Nangla (57)", "Phulera (46)", "Pishore Bhaike (34)", "Rai Dhariana (155)", "Ramgarh Sandhwan (63)", "Rampura Jawarwala (73)", "Ratta Khera (47)", "Rorewala (151)", "Sangatiwala (35)", "Sangatpura (53)", "Sheikhuwas (58)"], "Moonak": ["Andana (122)", "Babangarh Alias Ghamur Ghat (81)", "Badalgarh (96)", "Balran (82)", "Banarsi (127)", "Bangan (97)", "Baupur (125)", "Bazidpur (89)", "Bhathuwan (100)", "Bhulan (114)", "Bhundar Bhaini (101)", "Bhutal Khurd (92)", "Bishanpura Nauabad Alias Kokhar (109)", "Bushera (119)", "Chandu (120)", "Chatha Gobindpura (126)", "Dehla (91)", "Dhindsa (93)", "Dudian (94)", "Fatehgarh Nauabad Alias Bahmniwala (112)", "Ganota (107)", "Gobindgarh Alias Mahan Singhwala (111)", "Gobindpura Papra (90)", "Gulahri (115)", "Hamirgarh (99)", "Handa (84)", "Harigarh Gehlan (110)", "Jaswantpura Alias Hotipur (124)", "Kabirpur (87)", "Karail (83)", "Karoda (116)", "Khanauri Khurd (128)", "Kudni (85)", "Makorad (104)", "Mandvi (118)", "Maniana (108)", "Nawangaon (123)", "Phulad (105)", "Rajal Heri (98)", "Ramgarh Gujran (113)", "Rampura Gujran (86)", "Salemgarh (102)", "Shahpur Nauabad Alias Ther I (121)", "Shergarh Alias Sihan Singhwala (95)", "Surjan Bhaini (103)", "Thaska (117)"], "Sangrur": ["Akoi (21)", "Andheri (22)", "Badrukhan (16)", "Bahadarpur (66)", "Balian (28)", "Balwar Kalan (42)", "Banganwali (20)", "Bhagwanpura (34)", "Bhamabaddi (65)", "Bhindran (33)", "Bir Aishban (38)", "Bugar (82)", "Changal (18)", "Chatha Sekhwan (8)", "Deh Kalan (239)", "Dhadrian (77)", "Dialgarh (78)", "Duggan (67)", "Fatehgarh Chhanna (238)", "Gagarpur (55)", "Ghabdan (30)", "Gurdaspura (31)", "Hakikatpura (43)", "Illwal (44)", "Kalodi (32)", "Kammo Majra Khurd (36)", "Kammo Majra kalan (45)", "Kanoi (46)", "Kheri (47)", "Khilrian (19)", "Khurana (40)", "Khurani (41)", "Kular Khurd (51)", "Kunran (68)", "Laddi (29)", "Lidran (17)", "Loha Khera (1)", "Mander Kalan (3)", "Mander Khurd (81)", "Mangwal (35)", "Mohamadpur Risaldarwala (240)", "Nanakpura (26)", "Nankiana Sahib (24)", "Patti Bharaj (2)", "Qila Bharian (5)", "Ramnagar Sibian (37)", "Rattoke (74)", "Rupaheri (237)", "Sahoke (83)", "Saron (27)", "Sohian (39)", "Takipur (75)", "Thalesh (25)", "Togawal (76)", "Tung (48)", "Ubhawal (6)", "Upli (7)"], "Sunam": ["Akalgarh (50)", "Bakshiwala (27)", "Bhani Ganduan (42)", "Bharur (9)", "Biggarwal (53)", "Bir Kalan (16)", "Chamar Tibbi, Moranwali, Model Town ( R ) and Gugapeer, Kothe - Harigarh and Kothe Singhpur (OG)", "Chatha Nakta (49)", "Chatha Nanhera (31)", "Chhahar (33)", "Chhajla (39)", "Chhajli (36)", "Chowbas (22)", "Daula Singhwala (44)", "Dhaliwalbas (24)", "Dharamgarh (19)", "Gandwan (43)", "Ghanaur Jattan (100)", "Ghasiwala (26)", "Gobindgarh Jajian (56)", "Gobindpura Nagri (51)", "Hambalbas (23)", "Jakhepalbas (21)", "Jharon (14)", "Kahangarh (96)", "Kanakwal Bhangwan (45)", "Kauhrian (149)", "Khadial (1)", "Kotra Amru (25)", "Madewass (41)", "Mard Khera (52)", "Mauran (58)", "Mehlan (54)", "Mojowal (40)", "Namol (11)", "Nilowal (37)", "Ramgarh Jawanda (30)", "Ratolan (32)", "Rattangarh Alias Pattianwali (20)", "Sansarpura (29)", "Satoj (18)", "Shahpur Kalan (13)", "Shahpur Khurd Alias Lakhmirwala (10)", "Sheron (12) (Part)", "Taranji Khera (59)", "Tolawal (17)", "Ugrahan (38)"]}