{"Aalo HQ": ["Bene", "Biru (including Reyi Camp)", "Biru Doke", "Bogdo", "Darka", "Dego", "Eyi", "Gune Bane(including Popn Camp)", "Hissam", "Jimar", "Kabu", "Kamdi", "Kugi Pomse", "Kugi Pomte", "Logum Jini", "Pakam", "Panya", "Paya", "Pobdi", "Ragyi", "Ranaghat", "Rigo Kamdi", "Vivek Nagar (R.K. Mission)", "Wak", "Yeggo", "Yoji - Yora"], "Bagra Circle": ["Angu", "Bagra Higi", "Bagra Jeyi", "Bagra Lipu", "Bagra Takpu", "Doji Jeku", "Doyor", "Nigmoi", "Pigi Mengo", "Pigi Moli", "Yamko Bagra"], "Darak Circle": ["Bogo", "Boje Kigi-Pere", "Boje Lite", "Boje Pare", "Boru Raksap", "Darak", "Degi Potom", "Larmuk Potom", "Poyom", "Ravi", "Sala Potom", "Sijir Raksap"], "Kamba ADC": ["Balek Goli", "Boye", "Boyor Kam Dak", "DPG College Kamki Diet N.E. Farm Kamki", "Dego Kamki", "Gemo Kamku", "Gemo Tali", "Kamba H.Q.", "Kambu", "Kambu Moli", "Kamki", "Karbak Boyor", "Karbak Dabi", "Karbak Geyi", "Karbak Hipin(Karbak)", "Karbak Moli", "Karga", "Kato Moku", "Kato Namsi", "Keak", "Kesi Tali(Balek)", "Kunu Yami(Boye)", "Lipu Bene", "Nomuk", "Peri", "Ruyi", "Sere Tali", "Sesi Likar", "Sirutali", "Yakitato", "Yijogemo"], "Kombo Circle": ["Beye", "Doji Jelly", "Jirdin", "Kamen", "Kombo Papak", "Kombo Pomte(Kombo Monku)", "Kombo Tarsu Mobuk", "Ngomdir", "Pushi Doke", "Raglam", "Tadin"], "Liromoba EAC": ["Biri", "Bole Upper", "Bopu Lower", "Botak - Kayi", "Doko Putu", "Dordi", "Dumde Kayi", "Esse Kerte", "Esse Lipu", "Esse Taloh", "Esse Tamen", "Esse-Abe", "Kapen", "Khela Ronya", "Leggi", "Ligo", "Ligok Kayi", "Liromoba", "Liromoba H.Q.", "Lirum", "Moya Ronya", "Pokto", "Rikpu Ronya", "Rise", "Sari Likar"], "Nikte Kodum Circle": ["Berom Rime", "Dasi", "Hijum Rime", "Hu Moli(Eshi Moli)", "Igo Kato", "Igo Yami", "Nigi", "Nikte Camp", "Nyorak Rakte", "Old Rime", "Pidi Rime", "Pushi Nyorak", "Tabasora", "Yigi Kaum(Eshi Moku)"], "Yomcha ADC": ["Akker yomgam", "Belo", "Bopu Upper", "Daba Gamlin", "Denemisa", "Gadi Mesi", "Gamkak", "Jegar Yomcha", "Kadai", "Laggi Gamlin", "Lipu Yomcha", "Pagi Gamlin", "Tabyor Gadi", "Tapiyor", "Tego Gamlin", "Yomcha H.Q.", "Yomgam Kadai"]}